spro2tdtr/spro2tdtr.py
spro2tdtr-0.0.14.dist-info/LICENSE
spro2tdtr-0.0.14.dist-info/METADATA
spro2tdtr-0.0.14.dist-info/WHEEL
spro2tdtr-0.0.14.dist-info/entry_points.txt
spro2tdtr-0.0.14.dist-info/top_level.txt
spro2tdtr-0.0.14.dist-info/RECORD
