Metadata-Version: 2.1
Name: spro2tdtr
Version: 0.0.14
Summary: Extracts TOD data from .spro file and puts it in TDTR
Author-email: Dan Kennedy <dansherpa@gmail.com>
Project-URL: Homepage, https://github.com/dansherpa/spro2tdtr
Project-URL: Issues, https://github.com/dansherpa/spro2tdtr/issues
Classifier: Programming Language :: Python :: 3
Classifier: License :: OSI Approved :: MIT License
Classifier: Operating System :: OS Independent
Requires-Python: >=3.8
License-File: LICENSE
Requires-Dist: declxml
